{
    "wsh": {
        "starters": {
            "monte morris": {
                "pos": "PG",
                "inj": "-",
                "avgMin": 27,
                "ppg": 9.8,
                "apg": 5.2,
                "rpg": 3.4
            },
            "bradley beal": {
                "pos": "SG",
                "inj": "GTD",
                "avgMin": 35,
                "ppg": 22.9,
                "apg": 5.4,
                "rpg": 3.7
            },
            "deni avdija": {
                "pos": "SF",
                "inj": "-",
                "avgMin": 25,
                "ppg": 7.8,
                "apg": 2.7,
                "rpg": 5.3
            },
            "kyle kuzma": {
                "pos": "PF",
                "inj": "-",
                "avgMin": 34,
                "ppg": 21.4,
                "apg": 3.6,
                "rpg": 7.5
            },
            "kristaps porzingis": {
                "pos": "C",
                "inj": "-",
                "avgMin": 32,
                "ppg": 22.6,
                "apg": 2.6,
                "rpg": 8.9
            }
        },
        "injuries": {
            "bradley beal": {
                "pos": "G",
                "inj": "GTD",
                "avgMin": 35,
                "ppg": 22.9,
                "apg": 5.4,
                "rpg": 3.7
            },
            "rui hachimura": {
                "pos": "F",
                "inj": "OUT",
                "avgMin": 23,
                "ppg": 11.6,
                "apg": 1.1,
                "rpg": 4.8
            },
            "delon wright": {
                "pos": "G",
                "inj": "OUT",
                "avgMin": 23,
                "ppg": 6.5,
                "apg": 3.2,
                "rpg": 2.5
            }
        }
    },
    "lac": {
        "starters": {
            "reggie jackson": {
                "pos": "PG",
                "inj": "GTD",
                "avgMin": 29,
                "ppg": 12.4,
                "apg": 4.0,
                "rpg": 2.6
            },
            "paul george": {
                "pos": "SG",
                "inj": "GTD",
                "avgMin": 34,
                "ppg": 23.5,
                "apg": 4.9,
                "rpg": 6.3
            },
            "kawhi leonard": {
                "pos": "SF",
                "inj": "-",
                "avgMin": 26,
                "ppg": 13.7,
                "apg": 3.5,
                "rpg": 5.8
            },
            "marcus morris sr": {
                "pos": "PF",
                "inj": "-",
                "avgMin": 30,
                "ppg": 13.6,
                "apg": 1.8,
                "rpg": 4.9
            },
            "moses brown": {
                "pos": "C",
                "inj": "-",
                "avgMin": 6,
                "ppg": 3.9,
                "apg": 0.1,
                "rpg": 3.1
            }
        },
        "injuries": {
            "paul george": {
                "pos": "G",
                "inj": "GTD",
                "avgMin": 34,
                "ppg": 23.5,
                "apg": 4.9,
                "rpg": 6.3
            },
            "reggie jackson": {
                "pos": "G",
                "inj": "GTD",
                "avgMin": 29,
                "ppg": 12.4,
                "apg": 4.0,
                "rpg": 2.6
            },
            "norman powell": {
                "pos": "G",
                "inj": "OUT",
                "avgMin": 25,
                "ppg": 14.8,
                "apg": 1.5,
                "rpg": 2.9
            },
            "ivica zubac": {
                "pos": "C",
                "inj": "OUT",
                "avgMin": 29,
                "ppg": 10.1,
                "apg": 1.1,
                "rpg": 10.8
            }
        }
    },
    "mia": {
        "starters": {
            "jimmy butler": {
                "pos": "PG",
                "inj": "GTD",
                "avgMin": 35,
                "ppg": 21.6,
                "apg": 6.0,
                "rpg": 6.9
            },
            "tyler herro": {
                "pos": "SG",
                "inj": "-",
                "avgMin": 34,
                "ppg": 21.2,
                "apg": 4.1,
                "rpg": 6.3
            },
            "victor oladipo": {
                "pos": "SF",
                "inj": "-",
                "avgMin": 22,
                "ppg": 8.6,
                "apg": 2.8,
                "rpg": 3.0
            },
            "max strus": {
                "pos": "PF",
                "inj": "-",
                "avgMin": 31,
                "ppg": 13.5,
                "apg": 1.7,
                "rpg": 3.4
            },
            "bam adebayo": {
                "pos": "C",
                "inj": "-",
                "avgMin": 34,
                "ppg": 20.6,
                "apg": 3.3,
                "rpg": 9.7
            }
        },
        "injuries": {
            "jimmy butler": {
                "pos": "F",
                "inj": "GTD",
                "avgMin": 35,
                "ppg": 21.6,
                "apg": 6.0,
                "rpg": 6.9
            },
            "dewayne dedmon": {
                "pos": "C",
                "inj": "GTD",
                "avgMin": 12,
                "ppg": 6.6,
                "apg": 0.6,
                "rpg": 3.8
            },
            "udonis haslem": {
                "pos": "C",
                "inj": "GTD",
                "avgMin": 6,
                "ppg": 0.6,
                "apg": 0.0,
                "rpg": 1.2
            },
            "haywood highsmith": {
                "pos": "F",
                "inj": "GTD",
                "avgMin": 20,
                "ppg": 3.8,
                "apg": 0.9,
                "rpg": 4.3
            },
            "caleb martin": {
                "pos": "F",
                "inj": "GTD",
                "avgMin": 32,
                "ppg": 11.1,
                "apg": 1.9,
                "rpg": 4.7
            },
            "kyle lowry": {
                "pos": "G",
                "inj": "OUT",
                "avgMin": 36,
                "ppg": 14.0,
                "apg": 5.9,
                "rpg": 4.7
            },
            "gabe vincent": {
                "pos": "G",
                "inj": "OUT",
                "avgMin": 24,
                "ppg": 8.8,
                "apg": 2.9,
                "rpg": 2.1
            },
            "omer yurtseven": {
                "pos": "C",
                "inj": "OUT",
                "avgMin": 0,
                "ppg": 0,
                "apg": 0,
                "rpg": 0
            }
        }
    },
    "sa": {
        "starters": {
            "tre jones": {
                "pos": "PG",
                "inj": "-",
                "avgMin": 30,
                "ppg": 12.6,
                "apg": 6.6,
                "rpg": 3.4
            },
            "devin vassell": {
                "pos": "SG",
                "inj": "-",
                "avgMin": 31,
                "ppg": 19.9,
                "apg": 3.5,
                "rpg": 4.0
            },
            "keldon johnson": {
                "pos": "SF",
                "inj": "-",
                "avgMin": 32,
                "ppg": 21.0,
                "apg": 2.9,
                "rpg": 5.3
            },
            "keita bates diop": {
                "pos": "PF",
                "inj": "-",
                "avgMin": 19,
                "ppg": 8.5,
                "apg": 0.7,
                "rpg": 3.1
            },
            "jakob poeltl": {
                "pos": "C",
                "inj": "-",
                "avgMin": 27,
                "ppg": 12.8,
                "apg": 3.5,
                "rpg": 9.8
            }
        },
        "injuries": {
            "romeo langford": {
                "pos": "F",
                "inj": "OUT",
                "avgMin": 21,
                "ppg": 7.0,
                "apg": 1.0,
                "rpg": 3.2
            },
            "josh richardson": {
                "pos": "G",
                "inj": "OUT",
                "avgMin": 23,
                "ppg": 10.7,
                "apg": 2.9,
                "rpg": 2.4
            }
        }
    },
    "dal": {
        "starters": {
            "kemba walker": {
                "pos": "PG",
                "inj": "-",
                "avgMin": 16,
                "ppg": 7.0,
                "apg": 3.5,
                "rpg": 2.5
            },
            "reggie bullock": {
                "pos": "SG",
                "inj": "-",
                "avgMin": 27,
                "ppg": 5.1,
                "apg": 0.9,
                "rpg": 3.0
            },
            "tim hardaway": {
                "pos": "SF",
                "inj": "-",
                "avgMin": 0,
                "ppg": 0,
                "apg": 0,
                "rpg": 0
            },
            "dorian finney smith": {
                "pos": "PF",
                "inj": "-",
                "avgMin": 31,
                "ppg": 8.3,
                "apg": 1.1,
                "rpg": 4.0
            },
            "christian wood": {
                "pos": "C",
                "inj": "-",
                "avgMin": 26,
                "ppg": 17.2,
                "apg": 1.3,
                "rpg": 7.8
            }
        },
        "injuries": {
            "davis bertans": {
                "pos": "F",
                "inj": "GTD",
                "avgMin": 7,
                "ppg": 3.3,
                "apg": 0.4,
                "rpg": 0.7
            },
            "spencer dinwiddie": {
                "pos": "G",
                "inj": "OUT",
                "avgMin": 31,
                "ppg": 16.4,
                "apg": 5.3,
                "rpg": 3.3
            },
            "luka doncic": {
                "pos": "G",
                "inj": "OUT",
                "avgMin": 36,
                "ppg": 33.0,
                "apg": 8.7,
                "rpg": 8.3
            },
            "josh green": {
                "pos": "F",
                "inj": "OUT",
                "avgMin": 20,
                "ppg": 7.0,
                "apg": 1.2,
                "rpg": 2.3
            },
            "maxi kleber": {
                "pos": "F",
                "inj": "OUT",
                "avgMin": 25,
                "ppg": 6.2,
                "apg": 1.0,
                "rpg": 3.5
            },
            "dwight powell": {
                "pos": "C",
                "inj": "OUT",
                "avgMin": 16,
                "ppg": 5.7,
                "apg": 0.5,
                "rpg": 3.5
            }
        }
    },
    "cle": {
        "starters": {
            "darius garland": {
                "pos": "PG",
                "inj": "-",
                "avgMin": 35,
                "ppg": 21.0,
                "apg": 7.9,
                "rpg": 2.6
            },
            "donovan mitchell": {
                "pos": "SG",
                "inj": "-",
                "avgMin": 36,
                "ppg": 29.7,
                "apg": 4.6,
                "rpg": 3.8
            },
            "lamar stevens": {
                "pos": "SF",
                "inj": "GTD",
                "avgMin": 25,
                "ppg": 7.4,
                "apg": 0.6,
                "rpg": 4.4
            },
            "evan mobley": {
                "pos": "PF",
                "inj": "-",
                "avgMin": 34,
                "ppg": 15.0,
                "apg": 2.6,
                "rpg": 9.4
            },
            "jarrett allen": {
                "pos": "C",
                "inj": "-",
                "avgMin": 33,
                "ppg": 13.9,
                "apg": 1.4,
                "rpg": 10.0
            }
        },
        "injuries": {
            "lamar stevens": {
                "pos": "F",
                "inj": "GTD",
                "avgMin": 25,
                "ppg": 7.4,
                "apg": 0.6,
                "rpg": 4.4
            },
            "ricky rubio": {
                "pos": "G",
                "inj": "OUT",
                "avgMin": 0,
                "ppg": 0,
                "apg": 0,
                "rpg": 0
            },
            "dean wade": {
                "pos": "F",
                "inj": "OUT",
                "avgMin": 24,
                "ppg": 6.4,
                "apg": 1.0,
                "rpg": 4.1
            },
            "dylan windler": {
                "pos": "G",
                "inj": "OUT",
                "avgMin": 0,
                "ppg": 0,
                "apg": 0,
                "rpg": 0
            }
        }
    },
    "por": {
        "starters": {
            "damian lillard": {
                "pos": "PG",
                "inj": "-",
                "avgMin": 34,
                "ppg": 28.5,
                "apg": 6.9,
                "rpg": 3.9
            },
            "anfernee simons": {
                "pos": "SG",
                "inj": "-",
                "avgMin": 36,
                "ppg": 23.0,
                "apg": 4.4,
                "rpg": 3.0
            },
            "josh hart": {
                "pos": "SF",
                "inj": "-",
                "avgMin": 34,
                "ppg": 9.4,
                "apg": 3.9,
                "rpg": 8.2
            },
            "jerami grant": {
                "pos": "PF",
                "inj": "-",
                "avgMin": 35,
                "ppg": 21.9,
                "apg": 2.6,
                "rpg": 4.0
            },
            "jusuf nurkic": {
                "pos": "C",
                "inj": "-",
                "avgMin": 29,
                "ppg": 14.5,
                "apg": 2.8,
                "rpg": 10.1
            }
        },
        "injuries": {
            "gary payton": {
                "pos": "G",
                "inj": "GTD",
                "avgMin": 0,
                "ppg": 0,
                "apg": 0,
                "rpg": 0
            },
            "nassir little": {
                "pos": "F",
                "inj": "OUT",
                "avgMin": 15,
                "ppg": 5.5,
                "apg": 0.9,
                "rpg": 2.4
            }
        }
    },
    "hou": {
        "starters": {
            "kevin porter jr": {
                "pos": "PG",
                "inj": "-",
                "avgMin": 34,
                "ppg": 18.8,
                "apg": 5.7,
                "rpg": 5.6
            },
            "jalen green": {
                "pos": "SG",
                "inj": "-",
                "avgMin": 34,
                "ppg": 21.8,
                "apg": 3.8,
                "rpg": 4.2
            },
            "eric gordon": {
                "pos": "SF",
                "inj": "-",
                "avgMin": 29,
                "ppg": 12.1,
                "apg": 2.5,
                "rpg": 2.0
            },
            "jabari smith jr": {
                "pos": "PF",
                "inj": "-",
                "avgMin": 30,
                "ppg": 12.2,
                "apg": 0.7,
                "rpg": 7.2
            },
            "alperen sengun": {
                "pos": "C",
                "inj": "GTD",
                "avgMin": 26,
                "ppg": 14.3,
                "apg": 2.2,
                "rpg": 8.8
            }
        },
        "injuries": {
            "tari eason": {
                "pos": "F",
                "inj": "GTD",
                "avgMin": 18,
                "ppg": 8.4,
                "apg": 0.8,
                "rpg": 5.3
            },
            "alperen sengun": {
                "pos": "C",
                "inj": "GTD",
                "avgMin": 26,
                "ppg": 14.3,
                "apg": 2.2,
                "rpg": 8.8
            },
            "jaesean tate": {
                "pos": "F",
                "inj": "OUT",
                "avgMin": 22,
                "ppg": 8.3,
                "apg": 3.3,
                "rpg": 4.3
            }
        }
    },
    "utah": {
        "starters": {
            "mike conley": {
                "pos": "PG",
                "inj": "-",
                "avgMin": 29,
                "ppg": 10.1,
                "apg": 7.6,
                "rpg": 2.2
            },
            "jordan clarkson": {
                "pos": "SG",
                "inj": "-",
                "avgMin": 32,
                "ppg": 20.2,
                "apg": 4.7,
                "rpg": 3.9
            },
            "lauri markkanen": {
                "pos": "SF",
                "inj": "-",
                "avgMin": 34,
                "ppg": 22.4,
                "apg": 2.2,
                "rpg": 8.5
            },
            "jarred vanderbilt": {
                "pos": "PF",
                "inj": "-",
                "avgMin": 24,
                "ppg": 8.6,
                "apg": 2.8,
                "rpg": 8.2
            },
            "kelly olynyk": {
                "pos": "C",
                "inj": "-",
                "avgMin": 28,
                "ppg": 13.0,
                "apg": 3.3,
                "rpg": 5.1
            }
        },
        "injuries": {
            "collin sexton": {
                "pos": "G",
                "inj": "OUT",
                "avgMin": 24,
                "ppg": 14.3,
                "apg": 3.0,
                "rpg": 2.4
            }
        }
    },
    "mil": {
        "starters": {
            "jrue holiday": {
                "pos": "PG",
                "inj": "GTD",
                "avgMin": 32,
                "ppg": 19.1,
                "apg": 7.4,
                "rpg": 5.3
            },
            "jevon carter": {
                "pos": "SG",
                "inj": "-",
                "avgMin": 26,
                "ppg": 8.0,
                "apg": 3.3,
                "rpg": 2.8
            },
            "grayson allen": {
                "pos": "SF",
                "inj": "-",
                "avgMin": 27,
                "ppg": 10.8,
                "apg": 2.6,
                "rpg": 3.6
            },
            "giannis antetokounmpo": {
                "pos": "PF",
                "inj": "GTD",
                "avgMin": 32,
                "ppg": 30.6,
                "apg": 5.3,
                "rpg": 11.1
            },
            "brook lopez": {
                "pos": "C",
                "inj": "-",
                "avgMin": 30,
                "ppg": 13.9,
                "apg": 1.1,
                "rpg": 5.8
            }
        },
        "injuries": {
            "jrue holiday": {
                "pos": "G",
                "inj": "GTD",
                "avgMin": 32,
                "ppg": 19.1,
                "apg": 7.4,
                "rpg": 5.3
            },
            "giannis antetokounmpo": {
                "pos": "F",
                "inj": "GTD",
                "avgMin": 32,
                "ppg": 30.6,
                "apg": 5.3,
                "rpg": 11.1
            },
            "serge ibaka": {
                "pos": "C",
                "inj": "GTD",
                "avgMin": 11,
                "ppg": 4.3,
                "apg": 0.3,
                "rpg": 2.9
            },
            "joe ingles": {
                "pos": "F",
                "inj": "OUT",
                "avgMin": 0,
                "ppg": 0,
                "apg": 0,
                "rpg": 0
            },
            "khris middleton": {
                "pos": "G",
                "inj": "OUT",
                "avgMin": 24,
                "ppg": 11.1,
                "apg": 4.4,
                "rpg": 2.6
            }
        }
    },
    "mem": {
        "starters": {
            "ja morant": {
                "pos": "PG",
                "inj": "-",
                "avgMin": 32,
                "ppg": 27.6,
                "apg": 7.9,
                "rpg": 6.7
            },
            "dillon brooks": {
                "pos": "SG",
                "inj": "-",
                "avgMin": 30,
                "ppg": 17.7,
                "apg": 3.0,
                "rpg": 3.7
            },
            "john konchar": {
                "pos": "SF",
                "inj": "-",
                "avgMin": 27,
                "ppg": 8.3,
                "apg": 1.5,
                "rpg": 6.2
            },
            "jaren jackson jr": {
                "pos": "PF",
                "inj": "-",
                "avgMin": 25,
                "ppg": 17.2,
                "apg": 0.5,
                "rpg": 6.2
            },
            "steven adams": {
                "pos": "C",
                "inj": "-",
                "avgMin": 26,
                "ppg": 8.0,
                "apg": 2.3,
                "rpg": 10.3
            }
        },
        "injuries": {
            "desmond bane": {
                "pos": "G",
                "inj": "OUT",
                "avgMin": 33,
                "ppg": 24.7,
                "apg": 4.8,
                "rpg": 4.9
            },
            "danny green": {
                "pos": "G",
                "inj": "OUT",
                "avgMin": 0,
                "ppg": 0,
                "apg": 0,
                "rpg": 0
            }
        }
    },
    "okc": {
        "starters": {
            "josh giddey": {
                "pos": "PG",
                "inj": "-",
                "avgMin": 30,
                "ppg": 14.7,
                "apg": 5.5,
                "rpg": 8.1
            },
            "shai gilgeous alexander": {
                "pos": "SG",
                "inj": "-",
                "avgMin": 35,
                "ppg": 31.2,
                "apg": 5.8,
                "rpg": 4.7
            },
            "luguentz dort": {
                "pos": "SF",
                "inj": "GTD",
                "avgMin": 30,
                "ppg": 13.6,
                "apg": 2.4,
                "rpg": 4.4
            },
            "jalen williams": {
                "pos": "PF",
                "inj": "-",
                "avgMin": 26,
                "ppg": 11.1,
                "apg": 2.6,
                "rpg": 3.2
            },
            "darius bazley": {
                "pos": "C",
                "inj": "GTD",
                "avgMin": 17,
                "ppg": 5.9,
                "apg": 1.0,
                "rpg": 3.9
            }
        },
        "injuries": {
            "darius bazley": {
                "pos": "F",
                "inj": "GTD",
                "avgMin": 17,
                "ppg": 5.9,
                "apg": 1.0,
                "rpg": 3.9
            },
            "luguentz dort": {
                "pos": "F",
                "inj": "GTD",
                "avgMin": 30,
                "ppg": 13.6,
                "apg": 2.4,
                "rpg": 4.4
            },
            "kenrich williams": {
                "pos": "F",
                "inj": "GTD",
                "avgMin": 20,
                "ppg": 6.6,
                "apg": 1.4,
                "rpg": 3.8
            },
            "ousmane dieng": {
                "pos": "F",
                "inj": "OUT",
                "avgMin": 15,
                "ppg": 4.4,
                "apg": 1.4,
                "rpg": 2.9
            },
            "jeremiah robinson earl": {
                "pos": "C",
                "inj": "OUT",
                "avgMin": 21,
                "ppg": 8.5,
                "apg": 1.0,
                "rpg": 5.0
            }
        }
    },
    "no": {
        "starters": {
            "cj mccollum": {
                "pos": "PG",
                "inj": "-",
                "avgMin": 35,
                "ppg": 17.8,
                "apg": 5.6,
                "rpg": 5.0
            },
            "trey murphy": {
                "pos": "SG",
                "inj": "-",
                "avgMin": 0,
                "ppg": 0,
                "apg": 0,
                "rpg": 0
            },
            "herbert jones": {
                "pos": "SF",
                "inj": "-",
                "avgMin": 27,
                "ppg": 10.4,
                "apg": 2.2,
                "rpg": 3.5
            },
            "zion williamson": {
                "pos": "PF",
                "inj": "-",
                "avgMin": 32,
                "ppg": 25.3,
                "apg": 4.4,
                "rpg": 7.3
            },
            "jonas valanciunas": {
                "pos": "C",
                "inj": "-",
                "avgMin": 23,
                "ppg": 13.0,
                "apg": 1.8,
                "rpg": 9.1
            }
        },
        "injuries": {
            "jose alvarado": {
                "pos": "G",
                "inj": "GTD",
                "avgMin": 20,
                "ppg": 9.5,
                "apg": 3.2,
                "rpg": 2.2
            },
            "brandon ingram": {
                "pos": "F",
                "inj": "OUT",
                "avgMin": 32,
                "ppg": 20.8,
                "apg": 4.7,
                "rpg": 5.1
            },
            "ej liddell": {
                "pos": "F",
                "inj": "OUT",
                "avgMin": 0,
                "ppg": 0,
                "apg": 0,
                "rpg": 0
            }
        }
    },
    "phx": {
        "starters": {
            "chris paul": {
                "pos": "PG",
                "inj": "-",
                "avgMin": 31,
                "ppg": 10.7,
                "apg": 9.1,
                "rpg": 4.9
            },
            "devin booker": {
                "pos": "SG",
                "inj": "-",
                "avgMin": 35,
                "ppg": 26.9,
                "apg": 5.8,
                "rpg": 4.7
            },
            "mikal bridges": {
                "pos": "SF",
                "inj": "-",
                "avgMin": 36,
                "ppg": 16.2,
                "apg": 3.1,
                "rpg": 5.1
            },
            "torrey craig": {
                "pos": "PF",
                "inj": "-",
                "avgMin": 24,
                "ppg": 8.3,
                "apg": 1.4,
                "rpg": 5.2
            },
            "bismack biyombo": {
                "pos": "C",
                "inj": "-",
                "avgMin": 13,
                "ppg": 3.5,
                "apg": 0.9,
                "rpg": 3.6
            }
        },
        "injuries": {
            "deandre ayton": {
                "pos": "C",
                "inj": "OUT",
                "avgMin": 28,
                "ppg": 17.0,
                "apg": 2.2,
                "rpg": 9.5
            },
            "jae crowder": {
                "pos": "F",
                "inj": "OUT",
                "avgMin": 0,
                "ppg": 0,
                "apg": 0,
                "rpg": 0
            },
            "cameron johnson": {
                "pos": "F",
                "inj": "OUT",
                "avgMin": 25,
                "ppg": 13.0,
                "apg": 1.8,
                "rpg": 3.4
            },
            "cameron payne": {
                "pos": "G",
                "inj": "OUT",
                "avgMin": 24,
                "ppg": 12.7,
                "apg": 5.3,
                "rpg": 2.4
            },
            "duane washington": {
                "pos": "G",
                "inj": "OUT",
                "avgMin": 0,
                "ppg": 0,
                "apg": 0,
                "rpg": 0
            }
        }
    }
}