{
    "sam darnold": 36, 
    "ryan tannehill": 32, 
    "deshaun watson": 9, 
    "sam bradford": 30, 
    "nick foles": 29, 
    "marcus mariota": 19, 
    "tom brady": 3, 
    "mitchell trubisky": 28, 
    "case keenum": 27, 
    "matt ryan": 21, 
    "lamar jackson": 8, 
    "jimmy garoppolo": 26, 
    "alex smith": 20, 
    "tyrod taylor": 23, 
    "baker mayfield": 7, 
    "joe flacco": 34, 
    "drew brees": 4, 
    "russell wilson": 13, 
    "josh allen": 14, 
    "andrew luck": 15, 
    "dak prescott": 25, 
    "cam newton": 6, 
    "taysom hill": 2, 
    "patrick mahomes": 22, 
    "blake bortles": 24, 
    "jared goff": 17, 
    "eli manning": 35, 
    "blaine gabbert": 5, 
    "derek carr": 33, 
    "andy dalton": 16, 
    "ryan fitzpatrick": 31, 
    "aaron rodgers": 1, 
    "philip rivers": 11, 
    "kirk cousins": 12, 
    "matthew stafford": 10, 
    "ben roethlisberger": 18
}