{
    "kendrick bourne": 5.07, 
    "dallas goedert": 5.16, 
    "frank gore": 5.4, 
    "jordan wilkins": 5.91, 
    "jakeem grant": 4.59, 
    "ryan griffin": 4.51, 
    "terrelle pryor": 4.7, 
    "antonio gates": 5.1, 
    "corey clement": 5.8, 
    "tyler ervin": 5.63, 
    "chad williams": 4.72, 
    "cordarrelle patterson": 4.69, 
    "nick vannett": 5.74, 
    "jonnu smith": 4.55, 
    "josh doctson": 5.53, 
    "james washington": 5.71, 
    "rhett ellison": 5.74, 
    "ian thomas": 5.24, 
    "ricky seals-jones": 5.16, 
    "trent taylor": 4.85, 
    "courtland sutton": 5.88, 
    "michael gallup": 5.87, 
    "cody latimer": 5.58, 
    "geoff swaim": 5.9, 
    "ryan switzer": 4.51
}