{
    "amare barno": "DE",
    "raheem blackshear": "RB",
    "bradley bozeman": "OL",
    "derrick brown": "DT",
    "brian burns": "DE",
    "juston burris": "S",
    "sean chandler": "S",
    "brady christensen": "T",
    "larnel coleman": "T",
    "austin corbett": "OL",
    "sam darnold": "QB",
    "ikem ekwonu": "T",
    "cameron erving": "T",
    "donta foreman": "RB",
    "sam franklin": "S",
    "yetur gross-matos": "DE",
    "myles hartsfield": "DB",
    "tae hayes": "CB",
    "marquis haynes": "DE",
    "johnny hekker": "P",
    "cj henderson": "CB",
    "rashard higgins": "WR",
    "jaycee horn": "CB",
    "chuba hubbard": "RB",
    "matthew ioannidis": "DT",
    "jj jansen": "LS",
    "michael jordan": "G",
    "cory littleton": "LB",
    "frankie luvu": "LB",
    "terrace marshall": "WR",
    "baker mayfield": "QB",
    "cade mays": "G",
    "marquan mccall": "DT",
    "dj moore": "WR",
    "arron mosby": "LB",
    "taylor moton": "T",
    "daviyon nixon": "DT",
    "eddy pineiro": "K",
    "giovanni ricci": "FB",
    "bravvion roy": "DT",
    "laviska shenault": "WR",
    "brandon smith": "LB",
    "shi smith": "WR",
    "stephen sullivan": "TE",
    "keith taylor": "CB",
    "ian thomas": "TE",
    "shaq thompson": "LB",
    "tommy tremble": "TE",
    "pj walker": "QB",
    "damien wilson": "LB",
    "xavier woods": "S",
    "chandler wooten": "LB",
    "henry anderson (non)": "DE",
    "jeremy chinn (ird)": "S",
    "matt corral": "QB",
    "pat elflein": "G",
    "zane gonzalez": "K",
    "donte jackson": "CB",
    "andre roberts": "WR",
    "stantley thomas-oliver": "CB",
    "team total": ""
}