{
    "tyrell adams": "LB",
    "jordan akins": "TE",
    "bryan anger": "P",
    "eli ankou": "DT",
    "cornell armstrong": "CB",
    "ross blacklock": "DL",
    "pharaoh brown": "TE",
    "deandre carter": "WR",
    "randall cobb": "WR",
    "dylan cole": "LB",
    "brandin cooks": "WR",
    "keke coutee": "WR",
    "keion crossen": "CB",
    "zach cunningham": "OLB",
    "brandon dunn": "DT",
    "kyle emanuel": "OLB",
    "kaimi fairbairn": "K",
    "darren fells": "TE",
    "will fuller": "WR",
    "zach fulton": "OG",
    "phillip gaines": "CB",
    "cullen gillaspia": "RB",
    "jonathan greenard": "DL",
    "pj hall": "DT",
    "vernon hargreaves iii": "CB",
    "charlie heck": "OL",
    "tytus howard": "",
    "buddy howell": "RB",
    "david johnson": "RB",
    "duke johnson": "RB",
    "lonnie johnson": "CB",
    "roderick johnson": "OT",
    "peter kalambayi": "LB",
    "senio kelemete": "T",
    "jacob martin": "LB",
    "nick martin": "C",
    "aj mccarron": "QB",
    "whitney mercilus": "DE",
    "eric murray": "CB",
    "charles omenihu": "DL",
    "brent qvale": "T",
    "john reid": "CB",
    "justin reid": "FS",
    "bradley roby": "CB",
    "brennan scarlett": "LB",
    "max scharping": "OT",
    "kenny stills": "WR",
    "michael thomas": "S",
    "laremy tunsil": "OT",
    "carlos watkins": "DT",
    "deshaun watson": "QB",
    "jj watt": "DE",
    "jon weeks": "C",
    "team total": ""
}